commit_cartographer/__init__.py
commit_cartographer/git_activity.py
commit_cartographer/main.py
commit_cartographer/visualizers/__init__.py
commit_cartographer/visualizers/mermaid.py
commit_cartographer/visualizers/tree.py
commit_cartographer-0.1.9.dist-info/METADATA
commit_cartographer-0.1.9.dist-info/WHEEL
commit_cartographer-0.1.9.dist-info/entry_points.txt
commit_cartographer-0.1.9.dist-info/licenses/LICENSE
commit_cartographer-0.1.9.dist-info/RECORD
