Metadata-Version: 2.4
Name: commit-cartographer
Version: 0.1.9
Summary: A tool to visualize the commit history of a Git repository.
License-File: LICENSE
Requires-Python: >=3.10
Requires-Dist: click>=8.1.7
Requires-Dist: gitpython>=3.1.43
